{
  "id": "1d1a7fac-37e5-4718-895f-79da98a70ca7",
  "prevId": "eeb77570-7f85-4767-83bf-ccf6d332940b",
  "version": "5",
  "dialect": "pg",
  "tables": {
    "donations": {
      "name": "donations",
      "schema": "",
      "columns": {
        "id": {
          "name": "id",
          "type": "serial",
          "primaryKey": true,
          "notNull": true
        },
        "first_name": {
          "name": "first_name",
          "type": "varchar(255)",
          "primaryKey": false,
          "notNull": true
        },
        "last_name": {
          "name": "last_name",
          "type": "varchar(255)",
          "primaryKey": false,
          "notNull": true
        },
        "phone_number": {
          "name": "phone_number",
          "type": "varchar(255)",
          "primaryKey": false,
          "notNull": true
        },
        "sum": {
          "name": "sum",
          "type": "numeric(20, 2)",
          "primaryKey": false,
          "notNull": false
        }
      },
      "indexes": {},
      "foreignKeys": {},
      "compositePrimaryKeys": {},
      "uniqueConstraints": {}
    },
    "images": {
      "name": "images",
      "schema": "",
      "columns": {
        "id": {
          "name": "id",
          "type": "serial",
          "primaryKey": true,
          "notNull": true
        },
        "filename": {
          "name": "filename",
          "type": "varchar(24)",
          "primaryKey": false,
          "notNull": true
        },
        "width": {
          "name": "width",
          "type": "integer",
          "primaryKey": false,
          "notNull": true
        },
        "w_units": {
          "name": "w_units",
          "type": "varchar(12)",
          "primaryKey": false,
          "notNull": true
        },
        "height": {
          "name": "height",
          "type": "integer",
          "primaryKey": false,
          "notNull": true
        },
        "h_units": {
          "name": "h_units",
          "type": "varchar(12)",
          "primaryKey": false,
          "notNull": true
        },
        "mime_type": {
          "name": "mime_type",
          "type": "varchar(255)",
          "primaryKey": false,
          "notNull": true
        }
      },
      "indexes": {},
      "foreignKeys": {},
      "compositePrimaryKeys": {},
      "uniqueConstraints": {}
    },
    "pets": {
      "name": "pets",
      "schema": "",
      "columns": {
        "id": {
          "name": "id",
          "type": "serial",
          "primaryKey": true,
          "notNull": true
        },
        "type": {
          "name": "type",
          "type": "pet_type",
          "primaryKey": false,
          "notNull": true
        },
        "gender": {
          "name": "gender",
          "type": "gender",
          "primaryKey": false,
          "notNull": true
        },
        "name": {
          "name": "name",
          "type": "varchar(255)",
          "primaryKey": false,
          "notNull": true
        },
        "birth_date": {
          "name": "birth_date",
          "type": "timestamp with time zone",
          "primaryKey": false,
          "notNull": true
        },
        "description": {
          "name": "description",
          "type": "text",
          "primaryKey": false,
          "notNull": true
        },
        "image_id": {
          "name": "image_id",
          "type": "integer",
          "primaryKey": false,
          "notNull": true
        }
      },
      "indexes": {},
      "foreignKeys": {
        "pets_image_id_images_id_fk": {
          "name": "pets_image_id_images_id_fk",
          "tableFrom": "pets",
          "tableTo": "images",
          "schemaTo": "public",
          "columnsFrom": [
            "image_id"
          ],
          "columnsTo": [
            "id"
          ],
          "onDelete": "no action",
          "onUpdate": "no action"
        }
      },
      "compositePrimaryKeys": {},
      "uniqueConstraints": {}
    },
    "reservations": {
      "name": "reservations",
      "schema": "",
      "columns": {
        "id": {
          "name": "id",
          "type": "serial",
          "primaryKey": true,
          "notNull": true
        },
        "user_id": {
          "name": "user_id",
          "type": "integer",
          "primaryKey": false,
          "notNull": true
        },
        "pet_id": {
          "name": "pet_id",
          "type": "integer",
          "primaryKey": false,
          "notNull": true
        }
      },
      "indexes": {},
      "foreignKeys": {
        "reservations_user_id_users_user_id_fk": {
          "name": "reservations_user_id_users_user_id_fk",
          "tableFrom": "reservations",
          "tableTo": "users",
          "schemaTo": "public",
          "columnsFrom": [
            "user_id"
          ],
          "columnsTo": [
            "user_id"
          ],
          "onDelete": "no action",
          "onUpdate": "no action"
        },
        "reservations_pet_id_pets_id_fk": {
          "name": "reservations_pet_id_pets_id_fk",
          "tableFrom": "reservations",
          "tableTo": "pets",
          "schemaTo": "public",
          "columnsFrom": [
            "pet_id"
          ],
          "columnsTo": [
            "id"
          ],
          "onDelete": "no action",
          "onUpdate": "no action"
        }
      },
      "compositePrimaryKeys": {},
      "uniqueConstraints": {}
    },
    "users": {
      "name": "users",
      "schema": "",
      "columns": {
        "user_id": {
          "name": "user_id",
          "type": "serial",
          "primaryKey": true,
          "notNull": true
        },
        "login": {
          "name": "login",
          "type": "varchar(255)",
          "primaryKey": false,
          "notNull": true
        },
        "password": {
          "name": "password",
          "type": "varchar(72)",
          "primaryKey": false,
          "notNull": true
        },
        "status": {
          "name": "status",
          "type": "boolean",
          "primaryKey": false,
          "notNull": true
        }
      },
      "indexes": {},
      "foreignKeys": {},
      "compositePrimaryKeys": {},
      "uniqueConstraints": {}
    }
  },
  "enums": {
    "gender": {
      "name": "gender",
      "values": {
        "male": "male",
        "female": "female"
      }
    },
    "pet_type": {
      "name": "pet_type",
      "values": {
        "dog": "dog",
        "cat": "cat"
      }
    }
  },
  "schemas": {},
  "_meta": {
    "columns": {},
    "schemas": {},
    "tables": {}
  }
}